dbsnaplake/__init__.py
dbsnaplake/_import_utils.py
dbsnaplake/_version.py
dbsnaplake/api.py
dbsnaplake/compaction.py
dbsnaplake/constants.py
dbsnaplake/logger.py
dbsnaplake/partition.py
dbsnaplake/paths.py
dbsnaplake/polars_utils.py
dbsnaplake/project.py
dbsnaplake/s3_loc.py
dbsnaplake/snapshot_to_staging.py
dbsnaplake/staging_to_datalake.py
dbsnaplake/tracker.py
dbsnaplake/typehint.py
dbsnaplake/utils.py
dbsnaplake/validate_datalake.py
dbsnaplake/docs/__init__.py
dbsnaplake/tests/__init__.py
dbsnaplake/tests/data_faker.py
dbsnaplake/tests/helper.py
dbsnaplake/tests/mock_aws.py
dbsnaplake/vendor/__init__.py
dbsnaplake/vendor/pytest_cov_helper.py
dbsnaplake/vendor/timer.py
dbsnaplake/vendor/vislog/__init__.py
dbsnaplake/vendor/vislog/_version.py
dbsnaplake/vendor/vislog/impl.py
dbsnaplake/vendor/vislog/paths.py
dbsnaplake-0.3.2.dist-info/AUTHORS.rst
dbsnaplake-0.3.2.dist-info/LICENSE.txt
dbsnaplake-0.3.2.dist-info/METADATA
dbsnaplake-0.3.2.dist-info/WHEEL
dbsnaplake-0.3.2.dist-info/top_level.txt
dbsnaplake-0.3.2.dist-info/RECORD
