Metadata-Version: 2.1
Name: dbsnaplake
Version: 0.3.2
Summary: A framework that convert Any Database Snapshot to Analytical Friendly Data Lake.
Home-page: https://github.com/MacHu-GWU/dbsnaplake-project
Download-URL: https://pypi.python.org/pypi/dbsnaplake/0.3.2#downloads
Author: Sanhe Hu
Author-email: husanhe@gmail.com
Maintainer: Sanhe Hu
Maintainer-email: husanhe@email.com
License: GPL
Platform: Windows
Platform: MacOS
Platform: Unix
Classifier: Development Status :: 4 - Beta
Classifier: Intended Audience :: Developers
Classifier: License :: OSI Approved :: GNU General Public License (GPL)
Classifier: Natural Language :: English
Classifier: Operating System :: Microsoft :: Windows
Classifier: Operating System :: MacOS
Classifier: Operating System :: Unix
Classifier: Programming Language :: Python
Classifier: Programming Language :: Python :: 3.9
Classifier: Programming Language :: Python :: 3.10
Classifier: Programming Language :: Python :: 3.11
Classifier: Programming Language :: Python :: 3.12
Classifier: Programming Language :: Python :: 3 :: Only
Requires-Python: >=3.9
License-File: LICENSE.txt
License-File: AUTHORS.rst
Requires-Dist: polars <2.0.0,>=1.2.1
Requires-Dist: s3pathlib <3.0.0,>=2.2.1
Requires-Dist: s3manifesto <1.0.0,>=0.4.1
Requires-Dist: pynamodb-mate <7.0.0.0,>=6.0.0.4
Requires-Dist: polars-writer <1.0.0,>=0.3.1
Provides-Extra: docs
Requires-Dist: Sphinx ==5.3.0 ; extra == 'docs'
Requires-Dist: sphinx-jinja ==2.0.2 ; extra == 'docs'
Requires-Dist: sphinx-copybutton ==0.5.1 ; extra == 'docs'
Requires-Dist: sphinx-design ==0.5.0 ; extra == 'docs'
Requires-Dist: furo ==2023.03.27 ; extra == 'docs'
Requires-Dist: nbsphinx ==0.8.12 ; extra == 'docs'
Requires-Dist: rstobj ==1.2.1 ; extra == 'docs'
Requires-Dist: pygments ==2.15.1 ; extra == 'docs'
Requires-Dist: ipython ==8.10.0 ; extra == 'docs'
Requires-Dist: docfly ==2.0.3 ; extra == 'docs'
Provides-Extra: tests
Requires-Dist: pytest ; extra == 'tests'
Requires-Dist: pytest-cov ; extra == 'tests'
Requires-Dist: moto <6.0.0,>=5.0.0 ; extra == 'tests'
Requires-Dist: rich <14.0.0,>=13.4.2 ; extra == 'tests'
Requires-Dist: vislog <1.0.0,>=0.1.2 ; extra == 'tests'
Requires-Dist: numpy <2.0.0,>=1.26.4 ; extra == 'tests'
Requires-Dist: boto-session-manager <2.0.0,>=1.7.2 ; extra == 'tests'
Requires-Dist: deltalake <1.0.0,>=0.18.2 ; extra == 'tests'
